explanation_text/README.md
explanation_text/__init__.py
explanation_text/api_keys.json
explanation_text/explanation_generator_main.py
explanation_text/explanation_generator_utils.py
explanation_text/test_bench.py
explanation_text/explanation_generators/__init__.py
explanation_text/explanation_generators/api_utils.py
explanation_text/explanation_generators/rephraser.py
explanation_text/explanation_generators/api_test/__init__.py
explanation_text/explanation_generators/api_test/api_test.py
explanation_text/explanation_generators/api_test/api_test_setup.py
explanation_text/explanation_generators/explanation_generator_geoguesser/__init__.py
explanation_text/explanation_generators/explanation_generator_geoguesser/information_generator.py
explanation_text/explanation_generators/explanation_generator_geoguesser/main.py
explanation_text/explanation_generators/explanation_generator_geoguesser/overview.py
explanation_text/explanation_generators/explanation_generator_geoguesser/sentence_construction.py
explanation_text/explanation_generators/explanation_generator_geoguesser/knowledge_base/__init__.py
explanation_text/explanation_generators/explanation_generator_geoguesser/knowledge_base/knowledge_base_controller.py
explanation_text/explanation_generators/explanation_generator_geoguesser/knowledge_base/knowledge_base_filter.py
explanation_text/explanation_generators/explanation_generator_geoguesser/knowledge_base/landmark_detection.py
explanation_text/explanation_generators/explanation_generator_geoguesser/knowledge_base/wikipedia.py
explanation_text/explanation_generators/explanation_generator_geoguesser/knowledge_base/countries/alaska.txt
explanation_text/explanation_generators/explanation_generator_geoguesser/knowledge_base/countries/albania.txt
explanation_text/explanation_generators/explanation_generator_geoguesser/knowledge_base/countries/american_samoa.txt
explanation_text/explanation_generators/explanation_generator_geoguesser/knowledge_base/countries/andorra.txt
ExplanationText-0.2.2.dist-info/LICENSE
ExplanationText-0.2.2.dist-info/METADATA
ExplanationText-0.2.2.dist-info/WHEEL
ExplanationText-0.2.2.dist-info/top_level.txt
ExplanationText-0.2.2.dist-info/RECORD
