Metadata-Version: 2.1
Name: ExplanationText
Version: 0.2.2
Author-email: Tobias Litzenberger <tobias.litzenberger@tu-dortmund.de>, Celine Wald <celine.wald@tu-dortmund.de>, Alisa Gromova <alisa.gromova@tu-dortmund.de>
Classifier: Programming Language :: Python :: 3
Classifier: License :: OSI Approved :: MIT License
Classifier: Operating System :: OS Independent
Requires-Python: >=3.7
License-File: LICENSE
Requires-Dist: google-cloud-vision
Requires-Dist: requests
Requires-Dist: wikipedia-api
Requires-Dist: nltk
Requires-Dist: inflect
Requires-Dist: transformers
